kgforge/__init__.py
kgforge/config/__init__.py
kgforge/config/config.py
kgforge/data_models/__init__.py
kgforge/data_models/data_models.py
kgforge/kg/__init__.py
kgforge/kg/kg_construct.py
kgforge/utils/__init__.py
kgforge/utils/openalex_util.py
kgforge/utils/pdfreader.py
kgforge-0.2.11.dist-info/LICENSE
kgforge-0.2.11.dist-info/METADATA
kgforge-0.2.11.dist-info/WHEEL
kgforge-0.2.11.dist-info/RECORD
