Metadata-Version: 2.1
Name: kgforge
Version: 0.2.11
Summary: Library to automate extraction of scientific knowledge and generate knowledge graphs out of them.
License: MIT
Author: Harish Varma Siravuri
Author-email: harish.siravuri@gmail.com
Requires-Python: >=3.10,<4.0
Classifier: License :: OSI Approved :: MIT License
Classifier: Programming Language :: Python :: 3
Classifier: Programming Language :: Python :: 3.10
Classifier: Programming Language :: Python :: 3.11
Classifier: Programming Language :: Python :: 3.12
Requires-Dist: matplotlib (>=3.8.0,<4.0.0)
Requires-Dist: pdfminer (>=20191125,<20191126)
Requires-Dist: pydantic (>=2.4.2,<3.0.0)
Requires-Dist: pypdf2 (>=3.0.1,<4.0.0)
Requires-Dist: pytest (>=7.4.2,<8.0.0)
Requires-Dist: torch (>=2.0.0,!=2.0.1,!=2.1.0)
Requires-Dist: transformers (>=4.34.0,<5.0.0)
